Metadata-Version: 2.1
Name: AWSXenos
Version: 0.4.0
Summary: Scan and classify cross-account roles and resources in your AWS Account
Home-page: https://github.com/AirWalk-Digital/AWSXenos
Author: Costas Kourmpoglou
Author-email: costas.kourmpoglou@airwalkconsulting.com
License: MIT
Keywords: aws iam cross-account roles security
Classifier: Programming Language :: Python :: 3.10
Classifier: License :: OSI Approved :: MIT License
Classifier: Operating System :: OS Independent
Requires-Python: >=3.8
License-File: LICENSE
Requires-Dist: policyuniverse ==1.5.1.20231109
Requires-Dist: boto3 ==1.34.101
Requires-Dist: jinja2 ==3.1.4
Requires-Dist: pyyaml ==6.0.1
